[
  {
    "score": 0.9895570874214172,
    "part": "nose",
    "position": {
      "x": 213.22621683202365,
      "y": 126.43864295454804
    }
  },
  {
    "score": 0.9668421745300293,
    "part": "leftShoulder",
    "position": {
      "x": 252.00055786607794,
      "y": 154.0601753205177
    }
  },
  {
    "score": 0.9842283725738525,
    "part": "rightShoulder",
    "position": {
      "x": 189.48718119224222,
      "y": 162.95227899811147
    }
  },
  {
    "score": 0.9208989143371582,
    "part": "leftElbow",
    "position": {
      "x": 295.841031798129,
      "y": 115.34358985693073
    }
  },
  {
    "score": 0.9529362320899963,
    "part": "rightElbow",
    "position": {
      "x": 143.64475591637282,
      "y": 130.15710677803722
    }
  },
  {
    "score": 0.9137722849845886,
    "part": "leftWrist",
    "position": {
      "x": 273.13961400132234,
      "y": 62.68592242229773
    }
  },
  {
    "score": 0.9151149392127991,
    "part": "rightWrist",
    "position": {
      "x": 136.10733477521964,
      "y": 72.70538033214524
    }
  },
  {
    "score": 0.9988490343093872,
    "part": "leftHip",
    "position": {
      "x": 257.28767840314936,
      "y": 279.5567906004909
    }
  },
  {
    "score": 0.998529851436615,
    "part": "rightHip",
    "position": {
      "x": 208.08698869400916,
      "y": 284.56563767013847
    }
  },
  {
    "score": 0.9498892426490784,
    "part": "leftKnee",
    "position": {
      "x": 288.21989660597035,
      "y": 365.03735701861547
    }
  },
  {
    "score": 0.9211582541465759,
    "part": "rightKnee",
    "position": {
      "x": 170.95049015742796,
      "y": 365.0344246593431
    }
  },
  {
    "score": 0.9710971117019653,
    "part": "leftAnkle",
    "position": {
      "x": 282.5054925703353,
      "y": 438.4625009024653
    }
  },
  {
    "score": 0.9423007369041443,
    "part": "rightAnkle",
    "position": {
      "x": 149.81121582743722,
      "y": 439.0906354852223
    }
  }
]
